LICENSE
MANIFEST.in
README.md
quickfix.py
quickfix40.py
quickfix41.py
quickfix42.py
quickfix43.py
quickfix44.py
quickfix50.py
quickfix50sp1.py
quickfix50sp2.py
quickfixt11.py
setup.py
test_std_shared_ptr.cpp
test_std_tr1_shared_ptr.cpp
test_std_unique_ptr.cpp
C++/Acceptor.cpp
C++/Acceptor.h
C++/Allocator.h
C++/Application.h
C++/DOMDocument.h
C++/DataDictionary.cpp
C++/DataDictionary.h
C++/DataDictionaryProvider.cpp
C++/DataDictionaryProvider.h
C++/DatabaseConnectionID.h
C++/DatabaseConnectionPool.h
C++/Dictionary.cpp
C++/Dictionary.h
C++/Event.h
C++/Except.h
C++/Exceptions.h
C++/Field.h
C++/FieldConvertors.cpp
C++/FieldConvertors.h
C++/FieldMap.cpp
C++/FieldMap.h
C++/FieldNumbers.h
C++/FieldTypes.cpp
C++/FieldTypes.h
C++/Fields.h
C++/FileLog.cpp
C++/FileLog.h
C++/FileStore.cpp
C++/FileStore.h
C++/FixCommonFields.h
C++/FixFieldNumbers.h
C++/FixFields.h
C++/FixValues.h
C++/Group.cpp
C++/Group.h
C++/HostDetailsProvider.cpp
C++/HostDetailsProvider.h
C++/HtmlBuilder.h
C++/HttpConnection.cpp
C++/HttpConnection.h
C++/HttpMessage.cpp
C++/HttpMessage.h
C++/HttpParser.cpp
C++/HttpParser.h
C++/HttpServer.cpp
C++/HttpServer.h
C++/Initiator.cpp
C++/Initiator.h
C++/Log.cpp
C++/Log.h
C++/Message.cpp
C++/Message.h
C++/MessageCracker.h
C++/MessageSorters.cpp
C++/MessageSorters.h
C++/MessageStore.cpp
C++/MessageStore.h
C++/Mutex.h
C++/MySQLConnection.h
C++/MySQLLog.cpp
C++/MySQLLog.h
C++/MySQLStore.cpp
C++/MySQLStore.h
C++/NullStore.cpp
C++/NullStore.h
C++/OdbcConnection.h
C++/OdbcLog.cpp
C++/OdbcLog.h
C++/OdbcStore.cpp
C++/OdbcStore.h
C++/PUGIXML_DOMDocument.cpp
C++/PUGIXML_DOMDocument.h
C++/Parser.cpp
C++/Parser.h
C++/PostgreSQLConnection.h
C++/PostgreSQLLog.cpp
C++/PostgreSQLLog.h
C++/PostgreSQLStore.cpp
C++/PostgreSQLStore.h
C++/Queue.h
C++/QuickfixPython.cpp
C++/QuickfixPython.h
C++/Responder.h
C++/SSLSocketAcceptor.cpp
C++/SSLSocketAcceptor.h
C++/SSLSocketConnection.cpp
C++/SSLSocketConnection.h
C++/SSLSocketInitiator.cpp
C++/SSLSocketInitiator.h
C++/Session.cpp
C++/Session.h
quickfixpatch.egg-info/PKG-INFO
quickfixpatch.egg-info/SOURCES.txt
quickfixpatch.egg-info/dependency_links.txt
quickfixpatch.egg-info/top_level.txt
