Metadata-Version: 2.2
Name: quickfixpatch
Version: 6.0.0
Summary: FIX (Financial Information eXchange) protocol implementation
Home-page: http://www.quickfixengine.org
Download-URL: http://www.quickfixengine.org
Author: Ackley
Author-email: mackley@connamara.com
Maintainer: Ackley
Maintainer-email: mackley@connamara.com
License: The QuickFIX Software License, Version 1.0
License-File: LICENSE
Dynamic: author
Dynamic: author-email
Dynamic: download-url
Dynamic: home-page
Dynamic: license
Dynamic: maintainer
Dynamic: maintainer-email
Dynamic: summary
